[
  {
    "source_reference": {
      "file_name": "Copy_of_Copy_of_CRM_Call_Types_-_SERVICE_CATALOGUE_ServiceCategories_07_January_2026__V1_9.xlsx",
      "sheet_name": "Rea Vaya",
      "row_number": 2,
      "original_call_type_name": "DAMAGE ON BUS"
    },
    "call_type_code": "25001",
    "department": "Rea Vaya DAMAGE ON BUS",
    "service_group": "JOBURG SERVICES (Service Request)",
    "issue_category": "damage",
    "issue_type": "Damage on bus",
    "short_description": "BUS DAMAGE",
    "intent_bucket": "transport",
    "keywords": [
      "damage on",
      "on bus",
      "bus bus",
      "bus damage",
      "damage joburg",
      "joburg services",
      "services service",
      "service request",
      "damage on bus",
      "on bus bus",
      "bus bus damage",
      "bus damage joburg",
      "damage joburg services",
      "joburg services service",
      "services service request"
    ],
    "negative_keywords": [
      "account",
      "payment",
      "bill",
      "statement"
    ],
    "example_user_utterances": [
      "my bus damage",
      "I have bus damage",
      "there is bus damage"
    ],
    "confidence_weight": 0.7999999999999999,
    "min_confidence_required": 0.75
  },
  {
    "source_reference": {
      "file_name": "Copy_of_Copy_of_CRM_Call_Types_-_SERVICE_CATALOGUE_ServiceCategories_07_January_2026__V1_9.xlsx",
      "sheet_name": "Rea Vaya",
      "row_number": 3,
      "original_call_type_name": "CONTRACT HIRE CANCELLATION"
    },
    "call_type_code": "25002",
    "department": "Rea Vaya CONTRACT HIRE CANCELLATION",
    "service_group": "JOBURG SERVICES (Service Request)",
    "issue_category": "maintenance",
    "issue_type": "Contract hire cancellation",
    "short_description": "HIRE CANCELLATION",
    "intent_bucket": "transport",
    "keywords": [
      "contract hire",
      "hire cancellation",
      "cancellation hire",
      "cancellation joburg",
      "joburg services",
      "services service",
      "service request",
      "contract hire cancellation",
      "hire cancellation hire",
      "cancellation hire cancellation",
      "hire cancellation joburg",
      "cancellation joburg services",
      "joburg services service",
      "services service request",
      "contract"
    ],
    "negative_keywords": [],
    "example_user_utterances": [
      "my contract hire cancellation",
      "I have contract hire cancellation",
      "there is contract hire cancellation"
    ],
    "confidence_weight": 0.7999999999999999,
    "min_confidence_required": 0.75
  },
  {
    "source_reference": {
      "file_name": "Copy_of_Copy_of_CRM_Call_Types_-_SERVICE_CATALOGUE_ServiceCategories_07_January_2026__V1_9.xlsx",
      "sheet_name": "Rea Vaya",
      "row_number": 4,
      "original_call_type_name": "MECHANICAL BREAKDOWN"
    },
    "call_type_code": "25003",
    "department": "Rea Vaya MECHANICAL BREAKDOWN",
    "service_group": "JOBURG SERVICES (Service Request)",
    "issue_category": "maintenance",
    "issue_type": "Mechanical breakdown",
    "short_description": "MECHANICAL BREAKDOWN",
    "intent_bucket": "transport",
    "keywords": [
      "mechanical breakdown",
      "breakdown mechanical",
      "breakdown joburg",
      "joburg services",
      "services service",
      "service request",
      "mechanical breakdown mechanical",
      "breakdown mechanical breakdown",
      "mechanical breakdown joburg",
      "breakdown joburg services",
      "joburg services service",
      "services service request",
      "mechanical",
      "breakdown",
      "joburg"
    ],
    "negative_keywords": [],
    "example_user_utterances": [
      "my mechanical breakdown mechanical",
      "I have mechanical breakdown mechanical",
      "there is mechanical breakdown mechanical"
    ],
    "confidence_weight": 0.7999999999999999,
    "min_confidence_required": 0.75
  },
  {
    "source_reference": {
      "file_name": "Copy_of_Copy_of_CRM_Call_Types_-_SERVICE_CATALOGUE_ServiceCategories_07_January_2026__V1_9.xlsx",
      "sheet_name": "Rea Vaya",
      "row_number": 5,
      "original_call_type_name": "Rea Vaya NON ARRIVAL"
    },
    "call_type_code": "25004",
    "department": "Rea Vaya NON ARRIVAL",
    "service_group": "JOBURG SERVICES (Service Request)",
    "issue_category": "maintenance",
    "issue_type": "Rea vaya non arrival",
    "short_description": "BUS NON-ARRIVAL",
    "intent_bucket": "transport",
    "keywords": [
      "rea vaya",
      "vaya non",
      "non arrival",
      "arrival bus",
      "bus non",
      "arrival joburg",
      "joburg services",
      "services service",
      "service request",
      "rea vaya non",
      "vaya non arrival",
      "non arrival bus",
      "arrival bus non",
      "bus non arrival",
      "non arrival joburg"
    ],
    "negative_keywords": [],
    "example_user_utterances": [
      "my rea vaya non",
      "I have rea vaya non",
      "there is rea vaya non"
    ],
    "confidence_weight": 0.7999999999999999,
    "min_confidence_required": 0.75
  },
  {
    "source_reference": {
      "file_name": "Copy_of_Copy_of_CRM_Call_Types_-_SERVICE_CATALOGUE_ServiceCategories_07_January_2026__V1_9.xlsx",
      "sheet_name": "Rea Vaya",
      "row_number": 6,
      "original_call_type_name": "DAMAGED TAG"
    },
    "call_type_code": "25005",
    "department": "Rea Vaya DAMAGED TAG",
    "service_group": "JOBURG SERVICES (Service Request)",
    "issue_category": "damage",
    "issue_type": "Damaged tag",
    "short_description": "DAMAGED TAG",
    "intent_bucket": "transport",
    "keywords": [
      "damaged tag",
      "tag damaged",
      "tag joburg",
      "joburg services",
      "services service",
      "service request",
      "damaged tag damaged",
      "tag damaged tag",
      "damaged tag joburg",
      "tag joburg services",
      "joburg services service",
      "services service request",
      "damaged",
      "tag",
      "joburg"
    ],
    "negative_keywords": [
      "account",
      "payment",
      "bill",
      "statement"
    ],
    "example_user_utterances": [
      "my tag damage",
      "I have tag damage",
      "there is tag damage"
    ],
    "confidence_weight": 0.7999999999999999,
    "min_confidence_required": 0.75
  },
  {
    "source_reference": {
      "file_name": "Copy_of_Copy_of_CRM_Call_Types_-_SERVICE_CATALOGUE_ServiceCategories_07_January_2026__V1_9.xlsx",
      "sheet_name": "Rea Vaya",
      "row_number": 7,
      "original_call_type_name": "LOST TAG"
    },
    "call_type_code": "25006",
    "department": "Rea Vaya LOST TAG",
    "service_group": "JOBURG SERVICES (Service Request)",
    "issue_category": "maintenance",
    "issue_type": "Lost tag",
    "short_description": "LOST TAG",
    "intent_bucket": "transport",
    "keywords": [
      "lost tag",
      "tag lost",
      "tag joburg",
      "joburg services",
      "services service",
      "service request",
      "lost tag lost",
      "tag lost tag",
      "lost tag joburg",
      "tag joburg services",
      "joburg services service",
      "services service request",
      "lost",
      "tag",
      "joburg"
    ],
    "negative_keywords": [],
    "example_user_utterances": [
      "my lost tag lost",
      "I have lost tag lost",
      "there is lost tag lost"
    ],
    "confidence_weight": 0.7999999999999999,
    "min_confidence_required": 0.75
  },
  {
    "source_reference": {
      "file_name": "Copy_of_Copy_of_CRM_Call_Types_-_SERVICE_CATALOGUE_ServiceCategories_07_January_2026__V1_9.xlsx",
      "sheet_name": "Rea Vaya",
      "row_number": 8,
      "original_call_type_name": "PRIVATE HIRE CANCELLATION"
    },
    "call_type_code": "25007",
    "department": "Rea Vaya PRIVATE HIRE CANCELLATION",
    "service_group": "JOBURG SERVICES (Service Request)",
    "issue_category": "maintenance",
    "issue_type": "Private hire cancellation",
    "short_description": "HIRE CANCELLATION",
    "intent_bucket": "transport",
    "keywords": [
      "private hire",
      "hire cancellation",
      "cancellation hire",
      "cancellation joburg",
      "joburg services",
      "services service",
      "service request",
      "private hire cancellation",
      "hire cancellation hire",
      "cancellation hire cancellation",
      "hire cancellation joburg",
      "cancellation joburg services",
      "joburg services service",
      "services service request",
      "private"
    ],
    "negative_keywords": [],
    "example_user_utterances": [
      "my private hire cancellation",
      "I have private hire cancellation",
      "there is private hire cancellation"
    ],
    "confidence_weight": 0.7999999999999999,
    "min_confidence_required": 0.75
  },
  {
    "source_reference": {
      "file_name": "Copy_of_Copy_of_CRM_Call_Types_-_SERVICE_CATALOGUE_ServiceCategories_07_January_2026__V1_9.xlsx",
      "sheet_name": "Rea Vaya",
      "row_number": 9,
      "original_call_type_name": "PRIVATE HIRE RATES"
    },
    "call_type_code": "25008",
    "department": "Rea Vaya PRIVATE HIRE RATES",
    "service_group": "JOBURG SERVICES (Service Request)",
    "issue_category": "maintenance",
    "issue_type": "Private hire rates",
    "short_description": "HIRE RATES",
    "intent_bucket": "transport",
    "keywords": [
      "private hire",
      "hire rates",
      "rates hire",
      "rates joburg",
      "joburg services",
      "services service",
      "service request",
      "private hire rates",
      "hire rates hire",
      "rates hire rates",
      "hire rates joburg",
      "rates joburg services",
      "joburg services service",
      "services service request",
      "private"
    ],
    "negative_keywords": [],
    "example_user_utterances": [
      "my private hire rates",
      "I have private hire rates",
      "there is private hire rates"
    ],
    "confidence_weight": 0.7999999999999999,
    "min_confidence_required": 0.75
  },
  {
    "source_reference": {
      "file_name": "Copy_of_Copy_of_CRM_Call_Types_-_SERVICE_CATALOGUE_ServiceCategories_07_January_2026__V1_9.xlsx",
      "sheet_name": "Rea Vaya",
      "row_number": 10,
      "original_call_type_name": "CONTRACT HIRE SERVICE QUOTE"
    },
    "call_type_code": "25009",
    "department": "Rea Vaya CONTRACT HIRE SERVICE QUOTE",
    "service_group": "JOBURG SERVICES (Service Request)",
    "issue_category": "maintenance",
    "issue_type": "Contract hire service quote",
    "short_description": "HIRE SERVICE QUOTE",
    "intent_bucket": "transport",
    "keywords": [
      "contract hire",
      "hire service",
      "service quote",
      "quote hire",
      "quote joburg",
      "joburg services",
      "services service",
      "service request",
      "contract hire service",
      "hire service quote",
      "service quote hire",
      "quote hire service",
      "service quote joburg",
      "quote joburg services",
      "joburg services service"
    ],
    "negative_keywords": [],
    "example_user_utterances": [
      "my contract hire service",
      "I have contract hire service",
      "there is contract hire service"
    ],
    "confidence_weight": 0.7999999999999999,
    "min_confidence_required": 0.75
  },
  {
    "source_reference": {
      "file_name": "Copy_of_Copy_of_CRM_Call_Types_-_SERVICE_CATALOGUE_ServiceCategories_07_January_2026__V1_9.xlsx",
      "sheet_name": "Rea Vaya",
      "row_number": 11,
      "original_call_type_name": "LOST TRIPS"
    },
    "call_type_code": "25010",
    "department": "Rea Vaya LOST TRIPS",
    "service_group": "JOBURG SERVICES (Service Request)",
    "issue_category": "maintenance",
    "issue_type": "Lost trips",
    "short_description": "LOST TRIPS",
    "intent_bucket": "transport",
    "keywords": [
      "lost trips",
      "trips lost",
      "trips joburg",
      "joburg services",
      "services service",
      "service request",
      "lost trips lost",
      "trips lost trips",
      "lost trips joburg",
      "trips joburg services",
      "joburg services service",
      "services service request",
      "lost",
      "trips",
      "joburg"
    ],
    "negative_keywords": [],
    "example_user_utterances": [
      "my lost trips lost",
      "I have lost trips lost",
      "there is lost trips lost"
    ],
    "confidence_weight": 0.7999999999999999,
    "min_confidence_required": 0.75
  },
  {
    "source_reference": {
      "file_name": "Copy_of_Copy_of_CRM_Call_Types_-_SERVICE_CATALOGUE_ServiceCategories_07_January_2026__V1_9.xlsx",
      "sheet_name": "Rea Vaya",
      "row_number": 12,
      "original_call_type_name": "PRIVATE HIRE SERVICE QUOTE"
    },
    "call_type_code": "25011",
    "department": "Rea Vaya PRIVATE HIRE SERVICE QUOTE",
    "service_group": "JOBURG SERVICES (Service Request)",
    "issue_category": "maintenance",
    "issue_type": "Private hire service quote",
    "short_description": "HIRE SERVICE QUOTE",
    "intent_bucket": "transport",
    "keywords": [
      "private hire",
      "hire service",
      "service quote",
      "quote hire",
      "quote joburg",
      "joburg services",
      "services service",
      "service request",
      "private hire service",
      "hire service quote",
      "service quote hire",
      "quote hire service",
      "service quote joburg",
      "quote joburg services",
      "joburg services service"
    ],
    "negative_keywords": [],
    "example_user_utterances": [
      "my private hire service",
      "I have private hire service",
      "there is private hire service"
    ],
    "confidence_weight": 0.7999999999999999,
    "min_confidence_required": 0.75
  },
  {
    "source_reference": {
      "file_name": "Copy_of_Copy_of_CRM_Call_Types_-_SERVICE_CATALOGUE_ServiceCategories_07_January_2026__V1_9.xlsx",
      "sheet_name": "Rea Vaya",
      "row_number": 13,
      "original_call_type_name": "DAMAGED DESTINATION BOARD"
    },
    "call_type_code": "25012",
    "department": "Rea Vaya DAMAGED DESTINATION BOARD",
    "service_group": "JOBURG SERVICES (Service Request)",
    "issue_category": "damage",
    "issue_type": "Damaged destination board",
    "short_description": "DAMAGED DESTINATION BOARD",
    "intent_bucket": "transport",
    "keywords": [
      "damaged destination",
      "destination board",
      "board damaged",
      "board joburg",
      "joburg services",
      "services service",
      "service request",
      "damaged destination board",
      "destination board damaged",
      "board damaged destination",
      "destination board joburg",
      "board joburg services",
      "joburg services service",
      "services service request",
      "damaged"
    ],
    "negative_keywords": [
      "account",
      "payment",
      "bill",
      "statement"
    ],
    "example_user_utterances": [
      "my board damage",
      "I have board damage",
      "there is board damage"
    ],
    "confidence_weight": 0.7999999999999999,
    "min_confidence_required": 0.75
  },
  {
    "source_reference": {
      "file_name": "Copy_of_Copy_of_CRM_Call_Types_-_SERVICE_CATALOGUE_ServiceCategories_07_January_2026__V1_9.xlsx",
      "sheet_name": "Rea Vaya",
      "row_number": 14,
      "original_call_type_name": "MISSING DESTINATION BOARD"
    },
    "call_type_code": "25013",
    "department": "Rea Vaya MISSING DESTINATION BOARD",
    "service_group": "JOBURG SERVICES (Service Request)",
    "issue_category": "maintenance",
    "issue_type": "Missing destination board",
    "short_description": "MISSING DESTINATION BOARD",
    "intent_bucket": "transport",
    "keywords": [
      "missing destination",
      "destination board",
      "board missing",
      "board joburg",
      "joburg services",
      "services service",
      "service request",
      "missing destination board",
      "destination board missing",
      "board missing destination",
      "destination board joburg",
      "board joburg services",
      "joburg services service",
      "services service request",
      "missing"
    ],
    "negative_keywords": [],
    "example_user_utterances": [
      "my missing destination board",
      "I have missing destination board",
      "there is missing destination board"
    ],
    "confidence_weight": 0.7999999999999999,
    "min_confidence_required": 0.75
  },
  {
    "source_reference": {
      "file_name": "Copy_of_Copy_of_CRM_Call_Types_-_SERVICE_CATALOGUE_ServiceCategories_07_January_2026__V1_9.xlsx",
      "sheet_name": "Rea Vaya",
      "row_number": 15,
      "original_call_type_name": "PROBLEM PASSENGERS"
    },
    "call_type_code": "25014",
    "department": "Rea Vaya PROBLEM PASSENGERS",
    "service_group": "JOBURG SERVICES (Service Request)",
    "issue_category": "maintenance",
    "issue_type": "Problem passengers",
    "short_description": "PROBLEM PASSENGERS",
    "intent_bucket": "transport",
    "keywords": [
      "problem passengers",
      "passengers problem",
      "passengers joburg",
      "joburg services",
      "services service",
      "service request",
      "problem passengers problem",
      "passengers problem passengers",
      "problem passengers joburg",
      "passengers joburg services",
      "joburg services service",
      "services service request",
      "problem",
      "passengers",
      "joburg"
    ],
    "negative_keywords": [],
    "example_user_utterances": [
      "my problem passengers problem",
      "I have problem passengers problem",
      "there is problem passengers problem"
    ],
    "confidence_weight": 0.7999999999999999,
    "min_confidence_required": 0.75
  },
  {
    "source_reference": {
      "file_name": "Copy_of_Copy_of_CRM_Call_Types_-_SERVICE_CATALOGUE_ServiceCategories_07_January_2026__V1_9.xlsx",
      "sheet_name": "Rea Vaya",
      "row_number": 16,
      "original_call_type_name": "ROUTE EXTENSION"
    },
    "call_type_code": "25015",
    "department": "Rea Vaya ROUTE EXTENSION",
    "service_group": "JOBURG SERVICES (Service Request)",
    "issue_category": "maintenance",
    "issue_type": "Route extension",
    "short_description": "ROUTE EXTENSION",
    "intent_bucket": "transport",
    "keywords": [
      "route extension",
      "extension route",
      "extension joburg",
      "joburg services",
      "services service",
      "service request",
      "route extension route",
      "extension route extension",
      "route extension joburg",
      "extension joburg services",
      "joburg services service",
      "services service request",
      "route",
      "extension",
      "joburg"
    ],
    "negative_keywords": [],
    "example_user_utterances": [
      "my route extension route",
      "I have route extension route",
      "there is route extension route"
    ],
    "confidence_weight": 0.7999999999999999,
    "min_confidence_required": 0.75
  },
  {
    "source_reference": {
      "file_name": "Copy_of_Copy_of_CRM_Call_Types_-_SERVICE_CATALOGUE_ServiceCategories_07_January_2026__V1_9.xlsx",
      "sheet_name": "Rea Vaya",
      "row_number": 17,
      "original_call_type_name": "WRONG DESTINATION BOARD"
    },
    "call_type_code": "25016",
    "department": "Rea Vaya WRONG DESTINATION BOARD",
    "service_group": "JOBURG SERVICES (Service Request)",
    "issue_category": "maintenance",
    "issue_type": "Wrong destination board",
    "short_description": "WRONG DESTINATION BOARD",
    "intent_bucket": "transport",
    "keywords": [
      "wrong destination",
      "destination board",
      "board wrong",
      "board joburg",
      "joburg services",
      "services service",
      "service request",
      "wrong destination board",
      "destination board wrong",
      "board wrong destination",
      "destination board joburg",
      "board joburg services",
      "joburg services service",
      "services service request",
      "wrong"
    ],
    "negative_keywords": [],
    "example_user_utterances": [
      "my wrong destination board",
      "I have wrong destination board",
      "there is wrong destination board"
    ],
    "confidence_weight": 0.7999999999999999,
    "min_confidence_required": 0.75
  },
  {
    "source_reference": {
      "file_name": "Copy_of_Copy_of_CRM_Call_Types_-_SERVICE_CATALOGUE_ServiceCategories_07_January_2026__V1_9.xlsx",
      "sheet_name": "Rea Vaya",
      "row_number": 18,
      "original_call_type_name": "BUS OVERLOADING"
    },
    "call_type_code": "25017",
    "department": "Rea Vaya BUS OVERLOADING",
    "service_group": "JOBURG SERVICES (Service Request)",
    "issue_category": "maintenance",
    "issue_type": "Bus overloading",
    "short_description": "BUS OVERLOADING",
    "intent_bucket": "transport",
    "keywords": [
      "bus overloading",
      "overloading bus",
      "overloading joburg",
      "joburg services",
      "services service",
      "service request",
      "bus overloading bus",
      "overloading bus overloading",
      "bus overloading joburg",
      "overloading joburg services",
      "joburg services service",
      "services service request",
      "bus",
      "overloading",
      "joburg"
    ],
    "negative_keywords": [],
    "example_user_utterances": [
      "my bus overloading bus",
      "I have bus overloading bus",
      "there is bus overloading bus"
    ],
    "confidence_weight": 0.7999999999999999,
    "min_confidence_required": 0.75
  },
  {
    "source_reference": {
      "file_name": "Copy_of_Copy_of_CRM_Call_Types_-_SERVICE_CATALOGUE_ServiceCategories_07_January_2026__V1_9.xlsx",
      "sheet_name": "Rea Vaya",
      "row_number": 19,
      "original_call_type_name": "DIRTY BUS"
    },
    "call_type_code": "25018",
    "department": "Rea Vaya DIRTY BUS",
    "service_group": "JOBURG SERVICES (Service Request)",
    "issue_category": "quality",
    "issue_type": "Dirty bus",
    "short_description": "DIRTY BUS",
    "intent_bucket": "transport",
    "keywords": [
      "dirty bus",
      "bus dirty",
      "bus joburg",
      "joburg services",
      "services service",
      "service request",
      "dirty bus dirty",
      "bus dirty bus",
      "dirty bus joburg",
      "bus joburg services",
      "joburg services service",
      "services service request",
      "dirty",
      "bus",
      "joburg"
    ],
    "negative_keywords": [],
    "example_user_utterances": [
      "my dirty bus dirty",
      "I have dirty bus dirty",
      "there is dirty bus dirty"
    ],
    "confidence_weight": 0.7999999999999999,
    "min_confidence_required": 0.75
  },
  {
    "source_reference": {
      "file_name": "Copy_of_Copy_of_CRM_Call_Types_-_SERVICE_CATALOGUE_ServiceCategories_07_January_2026__V1_9.xlsx",
      "sheet_name": "Rea Vaya",
      "row_number": 20,
      "original_call_type_name": "DRIVER BEHAVIOUR"
    },
    "call_type_code": "25019",
    "department": "Rea Vaya DRIVER BEHAVIOUR",
    "service_group": "JOBURG SERVICES (Service Request)",
    "issue_category": "maintenance",
    "issue_type": "Driver behaviour",
    "short_description": "DRIVER BEHAVIOUR",
    "intent_bucket": "transport",
    "keywords": [
      "driver behaviour",
      "behaviour driver",
      "behaviour joburg",
      "joburg services",
      "services service",
      "service request",
      "driver behaviour driver",
      "behaviour driver behaviour",
      "driver behaviour joburg",
      "behaviour joburg services",
      "joburg services service",
      "services service request",
      "driver",
      "behaviour",
      "joburg"
    ],
    "negative_keywords": [],
    "example_user_utterances": [
      "my driver behaviour driver",
      "I have driver behaviour driver",
      "there is driver behaviour driver"
    ],
    "confidence_weight": 0.7999999999999999,
    "min_confidence_required": 0.75
  },
  {
    "source_reference": {
      "file_name": "Copy_of_Copy_of_CRM_Call_Types_-_SERVICE_CATALOGUE_ServiceCategories_07_January_2026__V1_9.xlsx",
      "sheet_name": "Rea Vaya",
      "row_number": 21,
      "original_call_type_name": "EARLY ARRIVAL OF BUS"
    },
    "call_type_code": "25020",
    "department": "Rea Vaya EARLY ARRIVAL OF BUS",
    "service_group": "JOBURG SERVICES (Service Request)",
    "issue_category": "maintenance",
    "issue_type": "Early arrival of bus",
    "short_description": "EARLY BUS ARRIVAL",
    "intent_bucket": "transport",
    "keywords": [
      "early arrival",
      "arrival of",
      "of bus",
      "bus early",
      "early bus",
      "bus arrival",
      "arrival joburg",
      "joburg services",
      "services service",
      "service request",
      "early arrival of",
      "arrival of bus",
      "of bus early",
      "bus early bus",
      "early bus arrival"
    ],
    "negative_keywords": [],
    "example_user_utterances": [
      "my early arrival of",
      "I have early arrival of",
      "there is early arrival of"
    ],
    "confidence_weight": 0.7999999999999999,
    "min_confidence_required": 0.75
  },
  {
    "source_reference": {
      "file_name": "Copy_of_Copy_of_CRM_Call_Types_-_SERVICE_CATALOGUE_ServiceCategories_07_January_2026__V1_9.xlsx",
      "sheet_name": "Rea Vaya",
      "row_number": 22,
      "original_call_type_name": "INCORRECT FARE CHARGE"
    },
    "call_type_code": "25021",
    "department": "Rea Vaya INCORRECT FARE CHARGE",
    "service_group": "JOBURG SERVICES (Service Request)",
    "issue_category": "maintenance",
    "issue_type": "Incorrect fare charge",
    "short_description": "INCORRECT FARE CHARGE",
    "intent_bucket": "transport",
    "keywords": [
      "incorrect fare",
      "fare charge",
      "charge incorrect",
      "charge joburg",
      "joburg services",
      "services service",
      "service request",
      "incorrect fare charge",
      "fare charge incorrect",
      "charge incorrect fare",
      "fare charge joburg",
      "charge joburg services",
      "joburg services service",
      "services service request",
      "incorrect"
    ],
    "negative_keywords": [],
    "example_user_utterances": [
      "my incorrect fare charge",
      "I have incorrect fare charge",
      "there is incorrect fare charge"
    ],
    "confidence_weight": 0.7999999999999999,
    "min_confidence_required": 0.75
  },
  {
    "source_reference": {
      "file_name": "Copy_of_Copy_of_CRM_Call_Types_-_SERVICE_CATALOGUE_ServiceCategories_07_January_2026__V1_9.xlsx",
      "sheet_name": "Rea Vaya",
      "row_number": 23,
      "original_call_type_name": "INJURY IN THE BUS"
    },
    "call_type_code": "25022",
    "department": "Rea Vaya INJURY IN THE BUS",
    "service_group": "JOBURG SERVICES (Service Request)",
    "issue_category": "maintenance",
    "issue_type": "Injury in the bus",
    "short_description": "INJURY ON BUS",
    "intent_bucket": "transport",
    "keywords": [
      "injury in",
      "the bus",
      "bus injury",
      "injury on",
      "on bus",
      "bus joburg",
      "joburg services",
      "services service",
      "service request",
      "injury in the",
      "in the bus",
      "the bus injury",
      "bus injury on",
      "injury on bus",
      "on bus joburg"
    ],
    "negative_keywords": [],
    "example_user_utterances": [
      "my injury in the",
      "I have injury in the",
      "there is injury in the"
    ],
    "confidence_weight": 0.7999999999999999,
    "min_confidence_required": 0.75
  },
  {
    "source_reference": {
      "file_name": "Copy_of_Copy_of_CRM_Call_Types_-_SERVICE_CATALOGUE_ServiceCategories_07_January_2026__V1_9.xlsx",
      "sheet_name": "Rea Vaya",
      "row_number": 24,
      "original_call_type_name": "INSPECTOR COMPLAINT"
    },
    "call_type_code": "25023",
    "department": "Rea Vaya INSPECTOR COMPLAINT",
    "service_group": "JOBURG SERVICES (Service Request)",
    "issue_category": "maintenance",
    "issue_type": "Inspector complaint",
    "short_description": "INSPECTOR COMPLAINT",
    "intent_bucket": "transport",
    "keywords": [
      "inspector complaint",
      "complaint inspector",
      "complaint joburg",
      "joburg services",
      "services service",
      "service request",
      "inspector complaint inspector",
      "complaint inspector complaint",
      "inspector complaint joburg",
      "complaint joburg services",
      "joburg services service",
      "services service request",
      "inspector",
      "complaint",
      "joburg"
    ],
    "negative_keywords": [],
    "example_user_utterances": [
      "my inspector complaint inspector",
      "I have inspector complaint inspector",
      "there is inspector complaint inspector"
    ],
    "confidence_weight": 0.7999999999999999,
    "min_confidence_required": 0.75
  },
  {
    "source_reference": {
      "file_name": "Copy_of_Copy_of_CRM_Call_Types_-_SERVICE_CATALOGUE_ServiceCategories_07_January_2026__V1_9.xlsx",
      "sheet_name": "Rea Vaya",
      "row_number": 25,
      "original_call_type_name": "Rea Vaya LATE ARRIVAL"
    },
    "call_type_code": "25024",
    "department": "Rea Vaya LATE ARRIVAL",
    "service_group": "JOBURG SERVICES (Service Request)",
    "issue_category": "maintenance",
    "issue_type": "Rea vaya late arrival",
    "short_description": "LATE ARRIVAL",
    "intent_bucket": "transport",
    "keywords": [
      "rea vaya",
      "vaya late",
      "late arrival",
      "arrival late",
      "arrival joburg",
      "joburg services",
      "services service",
      "service request",
      "rea vaya late",
      "vaya late arrival",
      "late arrival late",
      "arrival late arrival",
      "late arrival joburg",
      "arrival joburg services",
      "joburg services service"
    ],
    "negative_keywords": [],
    "example_user_utterances": [
      "my rea vaya late",
      "I have rea vaya late",
      "there is rea vaya late"
    ],
    "confidence_weight": 0.7999999999999999,
    "min_confidence_required": 0.75
  },
  {
    "source_reference": {
      "file_name": "Copy_of_Copy_of_CRM_Call_Types_-_SERVICE_CATALOGUE_ServiceCategories_07_January_2026__V1_9.xlsx",
      "sheet_name": "Rea Vaya",
      "row_number": 26,
      "original_call_type_name": "LOST PROPERTY"
    },
    "call_type_code": "25025",
    "department": "Rea Vaya LOST PROPERTY",
    "service_group": "JOBURG SERVICES (Service Request)",
    "issue_category": "maintenance",
    "issue_type": "Lost property",
    "short_description": "LOST PROPERTY",
    "intent_bucket": "transport",
    "keywords": [
      "lost property",
      "property lost",
      "property joburg",
      "joburg services",
      "services service",
      "service request",
      "lost property lost",
      "property lost property",
      "lost property joburg",
      "property joburg services",
      "joburg services service",
      "services service request",
      "lost",
      "property",
      "joburg"
    ],
    "negative_keywords": [],
    "example_user_utterances": [
      "my lost property lost",
      "I have lost property lost",
      "there is lost property lost"
    ],
    "confidence_weight": 0.7999999999999999,
    "min_confidence_required": 0.75
  },
  {
    "source_reference": {
      "file_name": "Copy_of_Copy_of_CRM_Call_Types_-_SERVICE_CATALOGUE_ServiceCategories_07_January_2026__V1_9.xlsx",
      "sheet_name": "Rea Vaya",
      "row_number": 27,
      "original_call_type_name": "LOUD RADIO"
    },
    "call_type_code": "25026",
    "department": "Rea Vaya LOUD RADIO",
    "service_group": "JOBURG SERVICES (Service Request)",
    "issue_category": "maintenance",
    "issue_type": "Loud radio",
    "short_description": "LOUD RADIO",
    "intent_bucket": "transport",
    "keywords": [
      "loud radio",
      "radio loud",
      "radio joburg",
      "joburg services",
      "services service",
      "service request",
      "loud radio loud",
      "radio loud radio",
      "loud radio joburg",
      "radio joburg services",
      "joburg services service",
      "services service request",
      "loud",
      "radio",
      "joburg"
    ],
    "negative_keywords": [],
    "example_user_utterances": [
      "my loud radio loud",
      "I have loud radio loud",
      "there is loud radio loud"
    ],
    "confidence_weight": 0.7999999999999999,
    "min_confidence_required": 0.75
  },
  {
    "source_reference": {
      "file_name": "Copy_of_Copy_of_CRM_Call_Types_-_SERVICE_CATALOGUE_ServiceCategories_07_January_2026__V1_9.xlsx",
      "sheet_name": "Rea Vaya",
      "row_number": 28,
      "original_call_type_name": "NO STOPPING"
    },
    "call_type_code": "25027",
    "department": "Rea Vaya NO STOPPING",
    "service_group": "JOBURG SERVICES (Service Request)",
    "issue_category": "maintenance",
    "issue_type": "No stopping",
    "short_description": "NO STOPPING",
    "intent_bucket": "transport",
    "keywords": [
      "no stopping",
      "stopping no",
      "stopping joburg",
      "joburg services",
      "services service",
      "service request",
      "no stopping no",
      "stopping no stopping",
      "no stopping joburg",
      "stopping joburg services",
      "joburg services service",
      "services service request",
      "stopping",
      "joburg",
      "services"
    ],
    "negative_keywords": [],
    "example_user_utterances": [
      "my no stopping",
      "I have no stopping",
      "there is no stopping"
    ],
    "confidence_weight": 0.7999999999999999,
    "min_confidence_required": 0.75
  },
  {
    "source_reference": {
      "file_name": "Copy_of_Copy_of_CRM_Call_Types_-_SERVICE_CATALOGUE_ServiceCategories_07_January_2026__V1_9.xlsx",
      "sheet_name": "Rea Vaya",
      "row_number": 29,
      "original_call_type_name": "NON-ISSUE OF TICKETS / IRREGULARITY"
    },
    "call_type_code": "25028",
    "department": "Rea Vaya NON-ISSUE OF TICKETS / IRREGULARITY",
    "service_group": "JOBURG SERVICES (Service Request)",
    "issue_category": "maintenance",
    "issue_type": "Non-issue of tickets / irregularity",
    "short_description": "TICKET IRREGULARITIES",
    "intent_bucket": "transport",
    "keywords": [
      "non issue",
      "issue of",
      "of tickets",
      "tickets irregularity",
      "irregularity ticket",
      "ticket irregularities",
      "irregularities joburg",
      "joburg services",
      "services service",
      "service request",
      "non issue of",
      "issue of tickets",
      "of tickets irregularity",
      "tickets irregularity ticket",
      "irregularity ticket irregularities"
    ],
    "negative_keywords": [],
    "example_user_utterances": [
      "my non-issue of tickets",
      "I have non-issue of tickets",
      "there is non-issue of tickets"
    ],
    "confidence_weight": 0.8999999999999999,
    "min_confidence_required": 0.65
  },
  {
    "source_reference": {
      "file_name": "Copy_of_Copy_of_CRM_Call_Types_-_SERVICE_CATALOGUE_ServiceCategories_07_January_2026__V1_9.xlsx",
      "sheet_name": "Rea Vaya",
      "row_number": 30,
      "original_call_type_name": "RECKLESS DRIVING"
    },
    "call_type_code": "25029",
    "department": "Rea Vaya RECKLESS DRIVING",
    "service_group": "JOBURG SERVICES (Service Request)",
    "issue_category": "maintenance",
    "issue_type": "Reckless driving",
    "short_description": "RECKLESS DRIVING",
    "intent_bucket": "transport",
    "keywords": [
      "reckless driving",
      "driving reckless",
      "driving joburg",
      "joburg services",
      "services service",
      "service request",
      "reckless driving reckless",
      "driving reckless driving",
      "reckless driving joburg",
      "driving joburg services",
      "joburg services service",
      "services service request",
      "reckless",
      "driving",
      "joburg"
    ],
    "negative_keywords": [],
    "example_user_utterances": [
      "my reckless driving reckless",
      "I have reckless driving reckless",
      "there is reckless driving reckless"
    ],
    "confidence_weight": 0.7999999999999999,
    "min_confidence_required": 0.75
  },
  {
    "source_reference": {
      "file_name": "Copy_of_Copy_of_CRM_Call_Types_-_SERVICE_CATALOGUE_ServiceCategories_07_January_2026__V1_9.xlsx",
      "sheet_name": "Rea Vaya",
      "row_number": 31,
      "original_call_type_name": "WRONG ROUTE TAKEN"
    },
    "call_type_code": "25030",
    "department": "Rea Vaya WRONG ROUTE TAKEN",
    "service_group": "JOBURG SERVICES (Service Request)",
    "issue_category": "maintenance",
    "issue_type": "Wrong route taken",
    "short_description": "WRONG ROUTE",
    "intent_bucket": "transport",
    "keywords": [
      "wrong route",
      "route taken",
      "taken wrong",
      "route joburg",
      "joburg services",
      "services service",
      "service request",
      "wrong route taken",
      "route taken wrong",
      "taken wrong route",
      "wrong route joburg",
      "route joburg services",
      "joburg services service",
      "services service request",
      "wrong"
    ],
    "negative_keywords": [],
    "example_user_utterances": [
      "my wrong route taken",
      "I have wrong route taken",
      "there is wrong route taken"
    ],
    "confidence_weight": 0.7999999999999999,
    "min_confidence_required": 0.75
  },
  {
    "source_reference": {
      "file_name": "Copy_of_Copy_of_CRM_Call_Types_-_SERVICE_CATALOGUE_ServiceCategories_07_January_2026__V1_9.xlsx",
      "sheet_name": "Rea Vaya",
      "row_number": 32,
      "original_call_type_name": "BUS STOP"
    },
    "call_type_code": "25031",
    "department": "Rea Vaya BUS STOP",
    "service_group": "JOBURG SERVICES (Service Request)",
    "issue_category": "maintenance",
    "issue_type": "Bus stop",
    "short_description": "BUS STOP",
    "intent_bucket": "transport",
    "keywords": [
      "bus stop",
      "stop bus",
      "stop joburg",
      "joburg services",
      "services service",
      "service request",
      "bus stop bus",
      "stop bus stop",
      "bus stop joburg",
      "stop joburg services",
      "joburg services service",
      "services service request",
      "bus",
      "stop",
      "joburg"
    ],
    "negative_keywords": [],
    "example_user_utterances": [
      "my bus stop bus",
      "I have bus stop bus",
      "there is bus stop bus"
    ],
    "confidence_weight": 0.7999999999999999,
    "min_confidence_required": 0.75
  },
  {
    "source_reference": {
      "file_name": "Copy_of_Copy_of_CRM_Call_Types_-_SERVICE_CATALOGUE_ServiceCategories_07_January_2026__V1_9.xlsx",
      "sheet_name": "Rea Vaya",
      "row_number": 33,
      "original_call_type_name": "DAMAGED BUS STOP"
    },
    "call_type_code": "25032",
    "department": "Rea Vaya DAMAGED BUS STOP",
    "service_group": "JOBURG SERVICES (Service Request)",
    "issue_category": "damage",
    "issue_type": "Damaged bus stop",
    "short_description": "DAMAGED BUS STOP",
    "intent_bucket": "transport",
    "keywords": [
      "damaged bus",
      "bus stop",
      "stop damaged",
      "stop joburg",
      "joburg services",
      "services service",
      "service request",
      "damaged bus stop",
      "bus stop damaged",
      "stop damaged bus",
      "bus stop joburg",
      "stop joburg services",
      "joburg services service",
      "services service request",
      "damaged"
    ],
    "negative_keywords": [
      "account",
      "payment",
      "bill",
      "statement"
    ],
    "example_user_utterances": [
      "my stop damage",
      "I have stop damage",
      "there is stop damage"
    ],
    "confidence_weight": 0.7999999999999999,
    "min_confidence_required": 0.75
  },
  {
    "source_reference": {
      "file_name": "Copy_of_Copy_of_CRM_Call_Types_-_SERVICE_CATALOGUE_ServiceCategories_07_January_2026__V1_9.xlsx",
      "sheet_name": "Rea Vaya",
      "row_number": 34,
      "original_call_type_name": "NEW ROUTE"
    },
    "call_type_code": "25033",
    "department": "Rea Vaya NEW ROUTE",
    "service_group": "JOBURG SERVICES (Service Request)",
    "issue_category": "maintenance",
    "issue_type": "New route",
    "short_description": "NEW ROUTE",
    "intent_bucket": "transport",
    "keywords": [
      "new route",
      "route new",
      "route joburg",
      "joburg services",
      "services service",
      "service request",
      "new route new",
      "route new route",
      "new route joburg",
      "route joburg services",
      "joburg services service",
      "services service request",
      "new",
      "route",
      "joburg"
    ],
    "negative_keywords": [],
    "example_user_utterances": [
      "my new route new",
      "I have new route new",
      "there is new route new"
    ],
    "confidence_weight": 0.7999999999999999,
    "min_confidence_required": 0.75
  }
]